setup.py
bin/noaa
noaa/__init__.py
noaa/exceptions.py
noaa/forecast.py
noaa/geocode.py
noaa/models.py
noaa/utils.py
noaa.egg-info/PKG-INFO
noaa.egg-info/SOURCES.txt
noaa.egg-info/dependency_links.txt
noaa.egg-info/top_level.txt